pbpstats/__init__.py
pbpstats/client.py
pbpstats/data_loader/__init__.py
pbpstats/data_loader/abs_data_loader.py
pbpstats/data_loader/data_nba/__init__.py
pbpstats/data_loader/data_nba/base.py
pbpstats/data_loader/data_nba/boxscore/__init__.py
pbpstats/data_loader/data_nba/boxscore/file.py
pbpstats/data_loader/data_nba/boxscore/loader.py
pbpstats/data_loader/data_nba/boxscore/web.py
pbpstats/data_loader/data_nba/enhanced_pbp/__init__.py
pbpstats/data_loader/data_nba/enhanced_pbp/file.py
pbpstats/data_loader/data_nba/enhanced_pbp/loader.py
pbpstats/data_loader/data_nba/enhanced_pbp/web.py
pbpstats/data_loader/data_nba/file_loader.py
pbpstats/data_loader/data_nba/pbp/__init__.py
pbpstats/data_loader/data_nba/pbp/file.py
pbpstats/data_loader/data_nba/pbp/loader.py
pbpstats/data_loader/data_nba/pbp/web.py
pbpstats/data_loader/data_nba/possessions/__init__.py
pbpstats/data_loader/data_nba/possessions/file.py
pbpstats/data_loader/data_nba/possessions/loader.py
pbpstats/data_loader/data_nba/possessions/web.py
pbpstats/data_loader/data_nba/schedule/__init__.py
pbpstats/data_loader/data_nba/schedule/file.py
pbpstats/data_loader/data_nba/schedule/loader.py
pbpstats/data_loader/data_nba/schedule/web.py
pbpstats/data_loader/data_nba/web_loader.py
pbpstats/data_loader/factory.py
pbpstats/data_loader/live/__init__.py
pbpstats/data_loader/live/base.py
pbpstats/data_loader/live/boxscore/__init__.py
pbpstats/data_loader/live/boxscore/file.py
pbpstats/data_loader/live/boxscore/loader.py
pbpstats/data_loader/live/boxscore/web.py
pbpstats/data_loader/live/enhanced_pbp/__init__.py
pbpstats/data_loader/live/enhanced_pbp/file.py
pbpstats/data_loader/live/enhanced_pbp/loader.py
pbpstats/data_loader/live/enhanced_pbp/web.py
pbpstats/data_loader/live/file_loader.py
pbpstats/data_loader/live/pbp/__init__.py
pbpstats/data_loader/live/pbp/file.py
pbpstats/data_loader/live/pbp/loader.py
pbpstats/data_loader/live/pbp/web.py
pbpstats/data_loader/live/possessions/__init__.py
pbpstats-1.3.11.dist-info/LICENSE
pbpstats-1.3.11.dist-info/WHEEL
pbpstats-1.3.11.dist-info/METADATA
pbpstats-1.3.11.dist-info/RECORD
