Metadata-Version: 2.1
Name: pbpstats
Version: 1.3.11
Summary: A package to scrape and parse NBA, WNBA and G-League play-by-play data
License: MIT
Author: dblackrun
Author-email: darryl.blackport@gmail.com
Requires-Python: >=3.8,<4.0
Classifier: License :: OSI Approved :: MIT License
Classifier: Programming Language :: Python :: 3
Classifier: Programming Language :: Python :: 3.10
Classifier: Programming Language :: Python :: 3.8
Classifier: Programming Language :: Python :: 3.9
Requires-Dist: requests (>=2.27.1,<3.0.0)
